{
	"schemaVersion": 1,
	"id": "create_enchantment_industry",
	"version": "1.0.0",
	"name": "Create: Enchantment Industry",
	"description": "An add-on for Create Fly, providing enchanting & experience related automation. Ported to 1.21.11.",
	"authors": [
		"MarbleGate",
		"RaymondBlaze"
	],
	"contact": {
		"sources": "https://github.com/DragonsPlusMinecraft/CreateEnchantmentIndustry"
	},
	"license": "LGPL-3.0-or-later",
	"environment": "*",
	"entrypoints": {
		"main": [
			"plus.dragons.createenchantmentindustry.EnchantmentIndustry"
		],
		"client": [
			"plus.dragons.createenchantmentindustry.client.EnchantmentIndustryClient"
		]
	},
	"accessWidener": "create_enchantment_industry.accesswidener",
	"depends": {
		"fabricloader": ">=0.19.3",
		"minecraft": "~1.21.11",
		"java": ">=21",
		"fabric-api": "*",
		"create": "*"
	}
}
